{"SafeNL":[{"?":true,"#":"imply_exclude","$":["imply","exclude"],"*":"boolean","~":{"or":[{"and":[{"==":[{"&":{"$":1},".":"state_1"},{"&":{"$":2},".":"state_1"}]},{"==":[{"&":{"$":1},".":"state_2"},{"&":{"$":2},".":"state_2"}]}]},{"and":[{"==":[{"&":{"$":1},".":"state_1"},{"&":{"$":2},".":"state_2"}]},{"==":[{"&":{"$":1},".":"state_2"},{"&":{"$":2},".":"state_1"}]}]}]}},{"?":true,"#":"coincide_forbid","$":["coincide","forbid"],"*":"boolean","~":{"or":[{"and":[{"==":[{"&":{"$":1},".":"event_1"},{"&":{"$":2},".":"event_2"}]},{"==":[{"&":{"$":1},".":"event_2"},{"&":{"$":2},".":"event_1"}]}]},{"and":[{"==":[{"&":{"$":1},".":"event_1"},{"&":{"$":2},".":"event_1"}]},{"==":[{"&":{"$":1},".":"event_2"},{"&":{"$":2},".":"event_2"}]}]}]}},{"?":true,"#":"permit_disallow","$":["permit","disallow"],"*":"boolean","~":{"and":[{"==":[{"&":{"$":1},".":"state_1"},{"&":{"$":2},".":"state_1"}]},{"==":[{"&":{"$":1},".":"event_2"},{"&":{"$":2},".":"event_2"}]}]}},{"?":true,"#":"permit_trigger","$":["permit","trigger"],"*":"boolean","~":{"and":[{"==":[{"&":{"$":1},".":"state_1"},{"&":{"$":2},".":"state_1"}]},{"==":[{"&":{"$":1},".":"event_2"},{"&":{"$":2},".":"event_2"}]}]}},{"?":true,"#":"disallow_terminate","$":["disallow","terminate"],"*":"boolean","~":{"and":[{"==":[{"&":{"$":1},".":"state_1"},{"&":{"$":2},".":"state_1"}]},{"==":[{"&":{"$":1},".":"event_2"},{"&":{"$":2},".":"event_2"}]}]}},{"?":true,"#":"trigger_terminate","$":["trigger","terminate"],"*":"boolean","~":{"and":[{"==":[{"&":{"$":1},".":"state_1"},{"&":{"$":2},".":"state_1"}]},{"==":[{"&":{"$":1},".":"event_2"},{"&":{"$":2},".":"event_2"}]},{"==":[{"&":{"$":1},".":"time_3"},{"&":{"$":2},".":"time_3"}]}]}}]}